vt_config/__init__.py
vt_config/config.py
vt_config-0.1.6.dist-info/METADATA
vt_config-0.1.6.dist-info/WHEEL
vt_config-0.1.6.dist-info/RECORD
