Metadata-Version: 2.4
Name: vt-config
Version: 0.1.6
Summary: Add your description here
Requires-Python: >=3.12
Requires-Dist: pydantic-settings>=2.8.1
Requires-Dist: pydantic>=2.11
Requires-Dist: python-dotenv>=1.1.0
